MANIFEST.in
README.rst
setup.py
docs/HISTORY.txt
docs/LICENSE.GPL
docs/LICENSE.txt
ftw/__init__.py
ftw.mobile.egg-info/PKG-INFO
ftw.mobile.egg-info/SOURCES.txt
ftw.mobile.egg-info/dependency_links.txt
ftw.mobile.egg-info/entry_points.txt
ftw.mobile.egg-info/namespace_packages.txt
ftw.mobile.egg-info/not-zip-safe
ftw.mobile.egg-info/requires.txt
ftw.mobile.egg-info/top_level.txt
ftw/mobile/__init__.py
ftw/mobile/buttons.py
ftw/mobile/buttons_multilingual.py
ftw/mobile/buttons_viewlet.py
ftw/mobile/configure.zcml
ftw/mobile/interfaces.py
ftw/mobile/navigation.py
ftw/mobile/testing.py
ftw/mobile/theming.zcml
ftw/mobile/locales/ftw.mobile.pot
ftw/mobile/locales/de/LC_MESSAGES/ftw.mobile.po
ftw/mobile/profiles/default/browserlayer.xml
ftw/mobile/profiles/default/jsregistry.xml
ftw/mobile/profiles/default/metadata.xml
ftw/mobile/profiles/default_plone5/browserlayer.xml
ftw/mobile/profiles/default_plone5/metadata.xml
ftw/mobile/profiles/default_plone5/registry.xml
ftw/mobile/resources/images/arrow-left.svg
ftw/mobile/resources/images/arrow-right.svg
ftw/mobile/resources/js/ftw-mobile-compiled.js
ftw/mobile/resources/js/hammer.js
ftw/mobile/resources/js/handlebars.js
ftw/mobile/resources/js/main.js
ftw/mobile/resources/js/navigation-button.js
ftw/mobile/resources/js/simple-buttons.js
ftw/mobile/scss/fastclick.scss
ftw/mobile/scss/layout.scss
ftw/mobile/scss/mobile-menu-buttons.scss
ftw/mobile/scss/mobile-menu.scss
ftw/mobile/templates/buttons_viewlet.pt
ftw/mobile/templates/list.html
ftw/mobile/templates/navigation.html
ftw/mobile/tests/__init__.py
ftw/mobile/tests/test_buttons.py
ftw/mobile/tests/test_buttons_viewlet.py
ftw/mobile/tests/test_multilingual_button.py
ftw/mobile/tests/test_navigation.py
ftw/mobile/tests/test_templates_rendered.py
ftw/mobile/tests/utils.py
ftw/mobile/upgrades/__init__.py
ftw/mobile/upgrades/20160517192445_fix_handlebars_compression/__init__.py
ftw/mobile/upgrades/20160517192445_fix_handlebars_compression/jsregistry.xml
ftw/mobile/upgrades/20160517192445_fix_handlebars_compression/upgrade.py
ftw/mobile/upgrades/20160706094752_fix_javascript_loading_order/__init__.py
ftw/mobile/upgrades/20160706094752_fix_javascript_loading_order/jsregistry.xml
ftw/mobile/upgrades/20160706094752_fix_javascript_loading_order/upgrade.py
