Metadata-Version: 2.1
Name: ftw.mobile
Version: 2.2.2
Summary: Mobile navigation and a basic infrastructure for mobile buttons on a Plone site.
Home-page: https://github.com/4teamwork/ftw.mobile
Author: 4teamwork AG
Author-email: mailto:info@4teamwork.ch
Maintainer: Mathias Leimgruber
License: GPL2
Keywords: ftw plone mobile navigation
Platform: UNKNOWN
Classifier: Framework :: Plone
Classifier: Framework :: Plone :: 4.3
Classifier: Framework :: Plone :: 5.1
Classifier: License :: OSI Approved :: GNU General Public License (GPL)
Classifier: Programming Language :: Python
Classifier: Programming Language :: Python :: 2.7
Classifier: Topic :: Software Development :: Libraries :: Python Modules
Provides-Extra: tests
Provides-Extra: test
